README.rst
setup.cfg
setup.py
./__init__.py
./channel.py
./channel.xml
./country.py
./party.py
./party.xml
./product.py
./product.xml
./sale.py
./tryton.cfg
./tests/__init__.py
./tests/test_base.py
./tests/test_channel.py
./tests/test_country.py
./tests/test_party.py
./tests/test_product.py
./tests/test_sale.py
./tests/test_views.py
./view/party_form.xml
./view/product_form.xml
./view/sale_channel_form.xml
./view/wizard_check_ebay_token_status_view_form.xml
trytond_ebay.egg-info/PKG-INFO
trytond_ebay.egg-info/SOURCES.txt
trytond_ebay.egg-info/dependency_links.txt
trytond_ebay.egg-info/entry_points.txt
trytond_ebay.egg-info/not-zip-safe
trytond_ebay.egg-info/requires.txt
trytond_ebay.egg-info/top_level.txt