Metadata-Version: 1.1
Name: trytond-ebay
Version: 3.4.8.0
Summary: eBay Integration
Home-page: http://openlabs.co.in/
Author: Openlabs Technologies and Consulting P Ltd.
Author-email: UNKNOWN
License: GPL-3
Download-URL: https://github.com/openlabs/trytond-ebay
Platform: UNKNOWN
Classifier: Development Status :: 4 - Beta
Classifier: Environment :: Plugins
Classifier: Framework :: Tryton
Classifier: Intended Audience :: Developers
Classifier: Intended Audience :: Financial and Insurance Industry
Classifier: Intended Audience :: Legal Industry
Classifier: Intended Audience :: Manufacturing
Classifier: License :: OSI Approved :: GNU General Public License (GPL)
Classifier: Natural Language :: English
Classifier: Operating System :: OS Independent
Classifier: Programming Language :: Python :: 2.7
Classifier: Topic :: Office/Business
